{
  "searchCount": 20,
  "searchParties": [
    {
      "areas": [],
      "category": "",
      "id": 551,
      "isKyc": false,
      "isScheduledToday": 1,
      "name": "RAGINI SINGH",
      "shortName": null,
      "specialities": []
    },
    {
      "areas": [],
      "category": "",
      "id": 772,
      "isKyc": false,
      "isScheduledToday": 1,
      "name": "RAHUL KISHORE",
      "shortName": null,
      "specialities": []
    },
    {
      "areas": [],
      "category": "",
      "id": 1946,
      "isKyc": false,
      "isScheduledToday": 1,
      "name": "RAHUL MAHESHWAR",
      "shortName": null,
      "specialities": []
    }
  ]
}
